bioto_client/__init__.py
bioto_client/__main__.py
bioto_client/cli.py
bioto_client/domain/__init__.py
bioto_client/domain/auth.py
bioto_client/domain/repository.py
bioto_client/domain/users.py
bioto_client/infrastructure/__init__.py
bioto_client/infrastructure/auth/__init__.py
bioto_client/infrastructure/auth/auth0.py
bioto_client/infrastructure/context.py
bioto_client/infrastructure/repository/api.py
bioto_client/infrastructure/users/__init__.py
bioto_client/infrastructure/users/users_session_storage.py
bioto_client-0.1.7.dist-info/LICENSE
bioto_client-0.1.7.dist-info/WHEEL
bioto_client-0.1.7.dist-info/entry_points.txt
bioto_client-0.1.7.dist-info/METADATA
bioto_client-0.1.7.dist-info/RECORD
