Metadata-Version: 2.1
Name: bioto-client
Version: 0.1.7
Summary: A python CLI client for accessing Bioto data
Author: Bioto
Author-email: it@bioto.co
Requires-Python: >=3.10,<4.0
Classifier: Programming Language :: Python :: 3
Classifier: Programming Language :: Python :: 3.10
Classifier: Programming Language :: Python :: 3.11
Requires-Dist: auth0-python (>=4.0.0,<5.0.0)
Requires-Dist: pydantic (>=1.10.4,<2.0.0)
Requires-Dist: python-dotenv (>=0.21.1,<0.22.0)
Requires-Dist: requests (>=2.28.2,<3.0.0)
Requires-Dist: typer[all] (>=0.7.0,<0.8.0)
